MC_API/MC_Arch.py
MC_API/__init__.py
MC_API-0.0.5.dist-info/METADATA
MC_API-0.0.5.dist-info/WHEEL
MC_API-0.0.5.dist-info/top_level.txt
MC_API-0.0.5.dist-info/RECORD
