Metadata-Version: 2.1
Name: MC-API
Version: 0.0.5
Summary: Es un paquete que te permitira obtener datos de un usuario de Minecraft y de los Servicios de Mojan y servidores de Minecraft
Home-page: https://github.com/fab-henao/MC.git
Author: Fabian Henao
Author-email: UNKNOWN
License: UNKNOWN
Keywords: mojang,minecraft,api,mojang api,minecraft api
Platform: UNKNOWN
Requires-Dist: requests
Requires-Dist: simple-colors
